helloworld/__init__.py
helloworld/hello.py
helloworlddojuan/__init__.py
helloworlddojuan/hello.py
helloworlddojuanz-1.0.0.dist-info/METADATA
helloworlddojuanz-1.0.0.dist-info/WHEEL
helloworlddojuanz-1.0.0.dist-info/top_level.txt
helloworlddojuanz-1.0.0.dist-info/RECORD
