Metadata-Version: 2.1
Name: helloworlddojuanz
Version: 1.0.0
Summary: Biblioteca de exemplo que imprime "Hello, World!"
Author: Juan
Author-email: juan.santanaa@outlook.com
